{
    "orders": [
        {
            "number_of_vehicle": 2,
            "vehicle_type": "LCV",
            "vehicle_size": null,
            "body_type": "Open",
            "packaging_type": "Drum",
            "pickup_address": "Vapi (GIDC)",
            "pickup_date_and_time": "Tonight @ 8 PM",
            "destination_address": "Surat (Ring Rd)",
            "expected_delivery_date_and_time": null,
            "product_category": "Plastic Drums",
            "product_description": "Plastic Drums (6 Tonnes total)",
            "total_weight": 6.0,
            "shippers_note": null,
            "pod_type": "Hardcopy"
        },
        {
            "number_of_vehicle": 1,
            "vehicle_type": "Trailer",
            "vehicle_size": null,
            "body_type": "Closed",
            "packaging_type": "Not specified",
            "pickup_address": "Hexa Cool Chakan",
            "pickup_date_and_time": "",
            "destination_address": "Hyderabad Central",
            "expected_delivery_date_and_time": null,
            "product_category": "Electronics",
            "product_description": "",
            "total_weight": 22.0,
            "shippers_note": null,
            "pod_type": "Hardcopy"
        }
    ]
}